{
  "version": "1.8.1",
  "description": "Code intelligence tool that builds semantic knowledge graphs from source code",
  "homepage": "https://github.com/aovestdipaperino/tokensave",
  "license": "MIT",
  "architecture": {
    "64bit": {
      "url": "https://github.com/aovestdipaperino/tokensave/releases/download/v1.8.1/tokensave-v1.8.1-x86_64-windows.zip",
      "hash": "38c196f748398e64dfcac606461f9459d0a5eab3b9212a6b038078624ecdfefc"
    }
  },
  "bin": "tokensave.exe",
  "checkver": {
    "github": "https://github.com/aovestdipaperino/tokensave"
  },
  "autoupdate": {
    "architecture": {
      "64bit": {
        "url": "https://github.com/aovestdipaperino/tokensave/releases/download/v$version/tokensave-v$version-x86_64-windows.zip"
      }
    }
  }
}
